s3_account_search/cli.py
s3_account_search-0.2.1.dist-info/entry_points.txt
s3_account_search-0.2.1.dist-info/LICENSE
s3_account_search-0.2.1.dist-info/WHEEL
s3_account_search-0.2.1.dist-info/METADATA
s3_account_search-0.2.1.dist-info/RECORD
