Metadata-Version: 2.1
Name: s3-account-search
Version: 0.2.1
Summary: Search for the AWS Account that contains an S3 bucket or object
Author: Ben Bridts
Requires-Python: >=3.7,<4.0
Classifier: Programming Language :: Python :: 3
Classifier: Programming Language :: Python :: 3.10
Classifier: Programming Language :: Python :: 3.7
Classifier: Programming Language :: Python :: 3.8
Classifier: Programming Language :: Python :: 3.9
Requires-Dist: aws-assume-role-lib (>=1.3.0,<2.0.0)
Requires-Dist: boto3 (>=1.16.49,<2.0.0)
